setup.py
pythonapp/__init__.py
pythonapp.egg-info/PKG-INFO
pythonapp.egg-info/SOURCES.txt
pythonapp.egg-info/dependency_links.txt
pythonapp.egg-info/not-zip-safe
pythonapp.egg-info/top_level.txt