Metadata-Version: 1.0
Name: pythonapp
Version: 0.1
Summary: pythonapp
Home-page: https://github.com/ignaciojluque/pythonapp
Author: Ignacio Luque
Author-email: flyingcircus@example.com
License: MIT
Platform: UNKNOWN
